{"version":"6.4","target":"Date::Calc","dist":"Date-Calc-6.4","provides":{"Date::Calendar::Profiles":{"file":"lib/Date/Calendar/Profiles.pm","version":"6.4"},"Date::Calendar":{"version":"6.4","file":"lib/Date/Calendar.pm"},"Date::Calc":{"file":"lib/Date/Calc.pm","version":"6.4"},"Date::Calendar::Year":{"file":"lib/Date/Calendar/Year.pm","version":"6.4"},"Date::Calc::PP":{"file":"lib/Date/Calc/PP.pm","version":"6.4"},"Date::Calc::Object":{"file":"lib/Date/Calc/Object.pm","version":"6.4"}},"pathname":"S/ST/STBEY/Date-Calc-6.4.tar.gz","name":"Date::Calc"}